storylinemapper/__init__.py
storylinemapper/cli.py
storylinemapper/html_generator.py
storylinemapper/network.py
storylinemapper/timeline.py
storylinemapper/utils.py
storylinemapper/community_analysis/__init__.py
storylinemapper/community_analysis/community.py
storylinemapper/network_analysis/__init__.py
storylinemapper/network_analysis/anomaly.py
storylinemapper/network_analysis/centrality.py
storylinemapper/network_analysis/metrics.py
storylinemapper/network_analysis/path.py
storylinemapper/network_analysis/structural_hole.py
storylinemapper/network_analysis/subgraph.py
storylinemapper-0.3.2.dist-info/LICENSE
storylinemapper-0.3.2.dist-info/METADATA
storylinemapper-0.3.2.dist-info/WHEEL
storylinemapper-0.3.2.dist-info/entry_points.txt
storylinemapper-0.3.2.dist-info/top_level.txt
storylinemapper-0.3.2.dist-info/RECORD
