Metadata-Version: 2.1
Name: storylinemapper
Version: 0.3.2
Summary: A library to generate networks of characters and timelines based on text
Home-page: https://github.com/kenjinezumi/storylinemapper
Author: Kenji Tsuchiya
Author-email: kenjitsuchiya1@gmail.com
Classifier: Programming Language :: Python :: 3
Classifier: Programming Language :: Python :: 3.12
Classifier: License :: OSI Approved :: MIT License
Classifier: Operating System :: OS Independent
Requires-Python: >=3.12
License-File: LICENSE
Requires-Dist: networkx <3.0,>=2.6
Requires-Dist: matplotlib <4.0,>=3.4
Requires-Dist: spacy <4.0,>=3.5
Requires-Dist: plotly <6.0,>=5.0
Requires-Dist: numpy >=1.15.0
Requires-Dist: scikit-learn <2.0,>=1.2
Requires-Dist: python-louvain >=0.16
Requires-Dist: infomap <2.0,>=1.5.0
Requires-Dist: community
Requires-Dist: infomap
